bluepyll/__init__.py
bluepyll/assets/adb_screenshot_img.png
bluepyll/assets/bluestacks_loading_img.png
bluepyll/assets/bluestacks_loading_screen_img.png
bluepyll/assets/bluestacks_my_games_button.png
bluepyll/assets/bluestacks_playstore_search_input.png
bluepyll/assets/bluestacks_store_button.png
bluepyll/assets/bluestacks_store_search_input.png
bluepyll/constants/__init__.py
bluepyll/constants/adb_constants.py
bluepyll/constants/bluestacks_constants.py
bluepyll/controller/__init__.py
bluepyll/controller/adb_controller.py
bluepyll/controller/bluepyll_controller.py
bluepyll/controller/bluestacks_controller.py
bluepyll/controller/image_controller.py
bluepyll/core/__init__.py
bluepyll/core/bluepyll_app.py
bluepyll/core/bluepyll_element.py
bluepyll/core/bluepyll_screen.py
bluepyll/exceptions.py
bluepyll/py.typed
bluepyll/state_machine.py
bluepyll/utils.py
bluepyll-0.1.15.dist-info/WHEEL
bluepyll-0.1.15.dist-info/METADATA
bluepyll-0.1.15.dist-info/RECORD
