Metadata-Version: 2.3
Name: bluepyll
Version: 0.1.15
Summary: A Python library designed to control BlueStacks through ADB commands, enabling seamless automation and management of Android applications on a PC.
Author: IAmNo1Special
Author-email: IAmNo1Special <ivmno1special@gmail.com>
Classifier: Development Status :: 4 - Beta
Classifier: Intended Audience :: Developers
Classifier: License :: OSI Approved :: MIT License
Classifier: Operating System :: Microsoft :: Windows
Classifier: Programming Language :: Python :: 3
Classifier: Programming Language :: Python :: 3.13
Classifier: Topic :: Software Development :: Libraries :: Python Modules
Classifier: Topic :: System :: Emulators
Classifier: Topic :: Utilities
Requires-Dist: adb-shell>=0.4.4
Requires-Dist: easyocr>=1.7.2
Requires-Dist: opencv-python>=4.11.0.86
Requires-Dist: pillow>=11.1.0
Requires-Dist: psutil>=7.0.0
Requires-Dist: pyautogui>=0.9.54
Requires-Dist: pywin32>=310
Requires-Dist: scikit-image>=0.25.2
Requires-Python: >=3.13
Project-URL: documentation, https://bluepyll.readthedocs.io
Project-URL: homepage, https://github.com/IAmNo1Special/BluePyll
Project-URL: issues, https://github.com/IAmNo1Special/BluePyll/issues
